aula_5/serial_out.vhd
-------------------------------------------------------------Unidade de Controle-------------------------------------------------------------
LIBRARY ieee;
USE ieee.numeric_bit.ALL;

ENTITY UC IS
    PORT (
        clock : IN BIT;
        reset, tx_go, tx_done : IN BIT;
        state_bit : OUT BIT
    );

END uc;

ARCHITECTURE behave_uc OF UC IS

    TYPE state IS (Swait, Ssend);
    SIGNAL current_state, next_state : state := Swait;
BEGIN

    PROCESS (clock)
    BEGIN
        IF (clock'event AND clock = '1') THEN
            current_state <= next_state;
        END IF;
    END PROCESS;

    next_state <= Swait WHEN (reset = '1') ELSE
        Ssend WHEN (tx_go = '1') ELSE
        next_state;

    PROCESS (current_state)
    BEGIN
        CASE current_state IS
            WHEN Swait =>
                state_bit <= '0';
            WHEN Ssend =>
                state_bit <= '1';
        END CASE;
    END PROCESS;
END behave_uc;

-------------------------------------------------------------Fluxo de Dados-----------------------------------------------------

LIBRARY ieee;
USE ieee.numeric_bit.ALL;

ENTITY FD IS
    GENERIC (
        POLARITY : BOOLEAN := true;
        width : NATURAL := 7;
        parity : NATURAL := 1;
        stop_bits : NATURAL := 1
    );
    PORT (
        clock : IN BIT;
        state : IN BIT;
        tx_done : OUT BIT;
        data : IN bit_vector(width - 1 DOWNTO 0);
        serial_o : OUT BIT
    );
END FD;

ARCHITECTURE behave_fd OF FD IS
    SIGNAL start_bit : BIT;
    SIGNAL counter : INTEGER := 0;
    SIGNAL all_data : bit_vector (width + stop_bits + parity DOWNTO 0); -- with start bit
    SIGNAL parity_bit : BIT := '0';
    SIGNAL backwards_data : bit_vector(width - 1 DOWNTO 0);
BEGIN
    start_bit <= '1' WHEN NOT polarity ELSE
        '0';

    PROCESS (state)
    BEGIN
        IF (state'event) AND (state = '1') THEN
            FOR i IN 0 TO width - 1 LOOP
                backwards_data(i) <= data(width - i - 1);
                parity_bit <= data(i) XOR parity_bit;
            END LOOP;
        ELSIF state = '0' THEN
            parity_bit <= '0';
        END IF;
    END PROCESS;

    all_data (width + parity + stop_bits DOWNTO stop_bits) <= start_bit & backwards_data & NOT parity_bit WHEN state = '1' ELSE
    (OTHERS => '1');

    all_data (stop_bits - 1 DOWNTO 0) <= (OTHERS => '1');

    PROCESS (clock)
    BEGIN
        IF (clock'event AND clock = '1') THEN

            IF state = '1' THEN
                serial_o <= all_data(counter);
            ELSE
                serial_o <= '1';
            END IF;

            IF state = '0' THEN
                counter <= width + stop_bits + parity;
                tx_done <= '0';
            ELSIF counter > 0 THEN
                counter <= counter - 1;
            ELSIF counter = 0 THEN
                tx_done <= '1';
            END IF;

        END IF;
    END PROCESS;
END behave_fd;

-------------------------------------------------------------serial_out-------------------------------------------------------------
LIBRARY ieee;
USE ieee.numeric_bit.ALL;

ENTITY serial_out IS
    GENERIC (
        POLARITY : BOOLEAN := true;
        width : NATURAL := 7;
        parity : NATURAL := 1;
        stop_bits : NATURAL := 1
    );
    PORT (
        clock : IN BIT;
        reset, tx_go : IN BIT;
        tx_done : OUT BIT;
        data : IN bit_vector(width - 1 DOWNTO 0);
        serial_o : OUT BIT
    );
END serial_out;

ARCHITECTURE behave_serial_out OF serial_out IS
    COMPONENT UC IS
        PORT (
            clock : IN BIT;
            reset, tx_go, tx_done : IN BIT;
            state_bit : OUT BIT
        );

    END COMPONENT;
    COMPONENT FD IS
        GENERIC (
            POLARITY : BOOLEAN := true;
            width : NATURAL := 7;
            parity : NATURAL := 1;
            stop_bits : NATURAL := 1
        );
        PORT (
            clock : IN BIT;
            state : IN BIT;
            tx_done : OUT BIT;
            data : IN bit_vector(width - 1 DOWNTO 0);
            serial_o : OUT BIT
        );
    END COMPONENT;

    SIGNAL inverted_clock, state, done : BIT := '0';
BEGIN
    inverted_clock <= NOT clock;
    tx_done <= done;
    FD_instance : FD GENERIC MAP(polarity, width, parity, stop_bits) PORT MAP(clock => inverted_clock, tx_done => done, state => state, data => data, serial_o => serial_o);
    UC_instance : UC PORT MAP(clock => clock, reset => reset, tx_go => tx_go, tx_done => done, state_bit => state);

END behave_serial_out;

aula_5/tx_tb.vhd
LIBRARY ieee;
USE ieee.numeric_bit.ALL;

ENTITY serial_out_tb IS
END serial_out_tb;

ARCHITECTURE behavior OF serial_out_tb IS
    -- Component Declaration for the Unit Under Test (UUT)
    COMPONENT serial_out
        GENERIC (
            POLARITY : BOOLEAN := TRUE;
            WIDTH : NATURAL := 8;
            PARITY : NATURAL := 1;
            STOP_BITS : NATURAL := 1
        );
        PORT (
            clock : IN BIT;
            reset : IN BIT;
            tx_go : IN BIT;
            tx_done : OUT BIT;
            data : IN bit_vector(WIDTH - 1 DOWNTO 0);
            serial_o : OUT BIT
        );
    END COMPONENT;

    COMPONENT serial_out2
        GENERIC (
            POLARITY : BOOLEAN := TRUE;
            WIDTH : NATURAL := 8;
            PARITY : NATURAL := 1;
            STOP_BITS : NATURAL := 1
        );
        PORT (
            clock : IN BIT;
            reset : IN BIT;
            tx_go : IN BIT;
            tx_done : OUT BIT;
            data : IN bit_vector(WIDTH - 1 DOWNTO 0);
            serial_o : OUT BIT
        );
    END COMPONENT;

    --Inputs
    SIGNAL clock : BIT := '0';
    SIGNAL reset : BIT := '0';
    SIGNAL tx_go : BIT := '0';
    SIGNAL data : bit_vector(7 DOWNTO 0);

    --Outputs
    SIGNAL tx_done : BIT;
    SIGNAL serial_o : BIT;
    -- Control
    SIGNAL finished : BIT := '0';
    CONSTANT half_period : TIME := 10 ns;

BEGIN

    dut : serial_out GENERIC MAP(
        POLARITY => TRUE,
        WIDTH => 8,
        PARITY => 1,
        STOP_BITS => 1
    )
    PORT MAP(
        clock => clock,
        reset => reset,
        tx_go => tx_go,
        tx_done => tx_done,
        data => data,
        serial_o => serial_o
    );

    clock <= NOT clock AFTER half_period WHEN finished /= '1' ELSE
        '0';
    test : PROCESS
    BEGIN
        ASSERT false REPORT "Inicio testes";

        data <= "11010101"; --Paridade 0
        reset <= '1';
        WAIT FOR 4 * half_period;
        reset <= '0';
        tx_go <= '1';
        WAIT UNTIL rising_edge(clock);

        WAIT UNTIL falling_edge(clock); --Amostra no meio do bit
        WAIT FOR 1 ns;
        ASSERT serial_o = '0'
        REPORT "Start Bit falhou";

        tx_go <= '0';

        FOR i IN data'reverse_range LOOP
            WAIT UNTIL falling_edge(clock);
            WAIT FOR 1 ns;
            ASSERT serial_o = data(i)
            REPORT "serial:" & BIT'image(serial_o) & ", esperado:" & BIT'image(data(i)) & "idx:" & INTEGER'image(i);
        END LOOP;

        WAIT UNTIL falling_edge(clock);
        WAIT FOR 1 ns;
        ASSERT serial_o = '0'
        REPORT "Teste Paridade Falhou";
        WAIT UNTIL falling_edge(clock);
        WAIT FOR 1 ns;
        ASSERT serial_o = '1'
        REPORT "Stop Bit falhou";
        WAIT FOR 1 ns;
        ASSERT tx_done = '1'
        REPORT "Done Falhou";

        REPORT "Fim teste transmissao inicial";

        WAIT FOR 10 * half_period;

        ASSERT tx_done = '1'
        REPORT "Done Deve se manter ligado";
        data <= "11010101"; --Paridade 0
        reset <= '1';
        WAIT FOR 4 * half_period;

        reset <= '0';
        tx_go <= '1';
        WAIT UNTIL rising_edge(clock);

        WAIT UNTIL falling_edge(clock); --Amostra no meio do bit
        WAIT FOR 1 ns;
        ASSERT serial_o = '0'
        REPORT "Start Bit falhou";

        FOR i IN data'reverse_range LOOP
            WAIT UNTIL falling_edge(clock);
            WAIT FOR 1 ns;
            ASSERT serial_o = data(i)
            REPORT "serial:" & BIT'image(serial_o) & ", esperado:" & BIT'image(data(i)) & "idx:" & INTEGER'image(i);
        END LOOP;

        WAIT UNTIL falling_edge(clock);
        WAIT FOR 1 ns;
        ASSERT serial_o = '0'
        REPORT "Teste Paridade Falhou";
        WAIT UNTIL falling_edge(clock);
        WAIT FOR 1 ns;
        ASSERT serial_o = '1'
        REPORT "Stop Bit falhou";

        REPORT "Fim teste reset e transmissao";
        WAIT FOR 10 * half_period;

        REPORT "Inicio teste metralhadora";

        data <= "11010101"; --Paridade 0
        reset <= '1';
        WAIT FOR 4 * half_period;

        reset <= '0';
        tx_go <= '1';
        WAIT UNTIL rising_edge(clock);

        FOR i IN 0 TO 2 LOOP
            WAIT UNTIL falling_edge(clock); --Amostra no meio do bit
            WAIT FOR 1 ns;
            ASSERT serial_o = '0'
            REPORT "Start Bit falhou";

            IF i = 2 THEN
                tx_go <= '0';
            END IF;

            FOR i IN data'reverse_range LOOP
                WAIT UNTIL falling_edge(clock);
                WAIT FOR 1 ns;
                ASSERT serial_o = data(i)
                REPORT "serial:" & BIT'image(serial_o) & ", esperado:" & BIT'image(data(i)) & "idx:" & INTEGER'image(i);
            END LOOP;

            WAIT UNTIL falling_edge(clock);
            WAIT FOR 1 ns;
            ASSERT serial_o = '0'
            REPORT "Teste Paridade Falhou";
            WAIT UNTIL falling_edge(clock);
            WAIT FOR 1 ns;
            ASSERT serial_o = '1'
            REPORT "Stop Bit falhou";
        END LOOP;
        REPORT "Fim teste metralhadora";
        WAIT FOR 10 * half_period;

        REPORT "Inicio teste swap data";

        data <= "00000000"; --Paridade 1
        reset <= '1';
        WAIT FOR 4 * half_period;

        reset <= '0';
        tx_go <= '1';
        WAIT UNTIL rising_edge(clock);
        WAIT UNTIL falling_edge(clock); --Amostra no meio do bit
        WAIT FOR 1 ns;
        ASSERT serial_o = '0'
        REPORT "Start Bit falhou";
        WAIT UNTIL falling_edge(clock); --Amostra no meio do bit
        WAIT FOR 1 ns;
        ASSERT serial_o = '0'
        REPORT "1 Bit falhou";
        WAIT UNTIL falling_edge(clock); --Amostra no meio do bit
        WAIT FOR 1 ns;
        ASSERT serial_o = '0'
        REPORT "2 Bit falhou";

        data <= "01111111"; -- Paridade 0

        WAIT UNTIL falling_edge(clock); --Amostra no meio do bit
        WAIT FOR 1 ns;
        ASSERT serial_o = '0'
        REPORT "3 Bit falhou";
        WAIT UNTIL falling_edge(clock); --Amostra no meio do bit
        WAIT FOR 1 ns;
        ASSERT serial_o = '0'
        REPORT "4 Bit falhou";
        WAIT UNTIL falling_edge(clock); --Amostra no meio do bit
        WAIT FOR 1 ns;
        ASSERT serial_o = '0'
        REPORT "5 Bit falhou";
        WAIT UNTIL falling_edge(clock); --Amostra no meio do bit
        WAIT FOR 1 ns;
        ASSERT serial_o = '0'
        REPORT "6 Bit falhou";
        WAIT UNTIL falling_edge(clock); --Amostra no meio do bit
        WAIT FOR 1 ns;
        ASSERT serial_o = '0'
        REPORT "7 Bit falhou";
        WAIT UNTIL falling_edge(clock); --Amostra no meio do bit
        WAIT FOR 1 ns;
        ASSERT serial_o = '0'
        REPORT "8 Bit falhou";
        WAIT UNTIL falling_edge(clock); --Amostra no meio do bit
        WAIT FOR 1 ns;
        ASSERT serial_o = '1'
        REPORT "Paridade Falhou";
        WAIT UNTIL falling_edge(clock); --Amostra no meio do bit
        WAIT FOR 1 ns;
        ASSERT serial_o = '1'
        REPORT "Stopbit Falhou";
        REPORT "Fim teste swap data";

        finished <= '1';
        WAIT;
    END PROCESS;
END behavior;

aula_5/res.vcd
$date
  Tue Apr  9 21:35:21 2024
$end
$version
  GHDL v0
$end
$timescale
  1 fs
$end
$scope module standard $end
$upscope $end
$scope module numeric_bit $end
$upscope $end
$scope module serial_out_tb $end
$var reg 1 ! clock $end
$var reg 1 " reset $end
$var reg 1 # tx_go $end
$var reg 8 $ data[7:0] $end
$var reg 1 % tx_done $end
$var reg 1 & serial_o $end
$var reg 1 ' finished $end
$scope module dut $end
$var reg 1 ( clock $end
$var reg 1 ) reset $end
$var reg 1 * tx_go $end
$var reg 1 + tx_done $end
$var reg 8 , data[7:0] $end
$var reg 1 - serial_o $end
$var reg 1 . inverted_clock $end
$var reg 1 / state $end
$var reg 1 0 done $end
$scope module fd_instance $end
$var reg 1 1 clock $end
$var reg 1 2 state $end
$var reg 1 3 tx_done $end
$var reg 8 4 data[7:0] $end
$var reg 1 5 serial_o $end
$var reg 1 6 start_bit $end
$var integer 32 7 counter $end
$var reg 11 8 all_data[10:0] $end
$var reg 1 9 parity_bit $end
$var reg 8 : backwards_data[7:0] $end
$upscope $end
$scope module uc_instance $end
$var reg 1 ; clock $end
$var reg 1 < reset $end
$var reg 1 = tx_go $end
$var reg 1 > tx_done $end
$var reg 1 ? state_bit $end
$comment current_state is not handled $end
$comment next_state is not handled $end
$upscope $end
$upscope $end
$upscope $end
$enddefinitions $end
#0
0!
1"
0#
b11010101 $
0%
1&
0'
0(
1)
0*
0+
b11010101 ,
1-
1.
0/
00
11
02
03
b11010101 4
15
06
b1010 7
b11111111111 8
09
b00000000 :
0;
1<
0=
0>
0?
#10000000
1!
1(
0.
01
1;
#20000000
0!
0(
1.
11
0;
#30000000
1!
1(
0.
01
1;
#40000000
0!
0"
1#
0(
0)
1*
1.
11
0;
0<
1=
#50000000
1!
1(
0.
1/
01
12
b01010101101 8
19
b10101011 :
1;
1?
#60000000
0!
0&
0(
0-
1.
11
05
b1001 7
0;
#61000000
0#
0*
0=
#70000000
1!
1(
0.
01
1;
#80000000
0!
1&
0(
1-
1.
11
15
b1000 7
0;
#81000000
#90000000
1!
1(
0.
01
1;
#100000000
0!
0&
0(
0-
1.
11
05
b111 7
0;
#101000000
#110000000
1!
1(
0.
01
1;
#120000000
0!
1&
0(
1-
1.
11
15
b110 7
0;
#121000000
#130000000
1!
1(
0.
01
1;
#140000000
0!
0&
0(
0-
1.
11
05
b101 7
0;
#141000000
#150000000
1!
1(
0.
01
1;
#160000000
0!
1&
0(
1-
1.
11
15
b100 7
0;
#161000000
#170000000
1!
1(
0.
01
1;
#180000000
0!
0&
0(
0-
1.
11
05
b11 7
0;
#181000000
#190000000
1!
1(
0.
01
1;
#200000000
0!
1&
0(
1-
1.
11
15
b10 7
0;
#201000000
#210000000
1!
1(
0.
01
1;
#220000000
0!
0(
1.
11
b1 7
0;
#221000000
#230000000
1!
1(
0.
01
1;
#240000000
0!
0&
0(
0-
1.
11
05
b0 7
0;
#241000000
#250000000
1!
1(
0.
01
1;
#260000000
0!
1%
1&
0(
1+
1-
1.
10
11
13
15
0;
1>
#261000000
#262000000
#270000000
1!
1(
0.
01
1;
#280000000
0!
0(
1.
11
0;
#290000000
1!
1(
0.
01
1;
#300000000
0!
0(
1.
11
0;
#310000000
1!
1(
0.
01
1;
#320000000
0!
0(
1.
11
0;
#330000000
1!
1(
0.
01
1;
#340000000
0!
0(
1.
11
0;
#350000000
1!
1(
0.
01
1;
#360000000
0!
0(
1.
11
0;
#362000000
1"
1)
1<
#370000000
1!
1(
0.
0/
01
02
b11111111111 8
09
1;
0?
#380000000
0!
0%
0(
0+
1.
00
11
03
b1010 7
0;
0>
#390000000
1!
1(
0.
01
1;
#400000000
0!
0(
1.
11
0;
#402000000
0"
1#
0)
1*
0<
1=
#410000000
1!
1(
0.
1/
01
12
b01010101101 8
19
1;
1?
#420000000
0!
0&
0(
0-
1.
11
05
b1001 7
0;
#421000000
#430000000
1!
1(
0.
01
1;
#440000000
0!
1&
0(
1-
1.
11
15
b1000 7
0;
#441000000
#450000000
1!
1(
0.
01
1;
#460000000
0!
0&
0(
0-
1.
11
05
b111 7
0;
#461000000
#470000000
1!
1(
0.
01
1;
#480000000
0!
1&
0(
1-
1.
11
15
b110 7
0;
#481000000
#490000000
1!
1(
0.
01
1;
#500000000
0!
0&
0(
0-
1.
11
05
b101 7
0;
#501000000
#510000000
1!
1(
0.
01
1;
#520000000
0!
1&
0(
1-
1.
11
15
b100 7
0;
#521000000
#530000000
1!
1(
0.
01
1;
#540000000
0!
0&
0(
0-
1.
11
05
b11 7
0;
#541000000
#550000000
1!
1(
0.
01
1;
#560000000
0!
1&
0(
1-
1.
11
15
b10 7
0;
#561000000
#570000000
1!
1(
0.
01
1;
#580000000
0!
0(
1.
11
b1 7
0;
#581000000
#590000000
1!
1(
0.
01
1;
#600000000
0!
0&
0(
0-
1.
11
05
b0 7
0;
#601000000
#610000000
1!
1(
0.
01
1;
#620000000
0!
1%
1&
0(
1+
1-
1.
10
11
13
15
0;
1>
#621000000
#630000000
1!
1(
0.
01
1;
#640000000
0!
0(
1.
11
0;
#650000000
1!
1(
0.
01
1;
#660000000
0!
0(
1.
11
0;
#670000000
1!
1(
0.
01
1;
#680000000
0!
0(
1.
11
0;
#690000000
1!
1(
0.
01
1;
#700000000
0!
0(
1.
11
0;
#710000000
1!
1(
0.
01
1;
#720000000
0!
0(
1.
11
0;
#721000000
1"
1)
1<
#730000000
1!
1(
0.
0/
01
02
b11111111111 8
09
1;
0?
#740000000
0!
0%
0(
0+
1.
00
11
03
b1010 7
0;
0>
#750000000
1!
1(
0.
01
1;
#760000000
0!
0(
1.
11
0;
#761000000
0"
0)
0<
#770000000
1!
1(
0.
1/
01
12
b01010101101 8
19
1;
1?
#780000000
0!
0&
0(
0-
1.
11
05
b1001 7
0;
#781000000
#790000000
1!
1(
0.
01
1;
#800000000
0!
1&
0(
1-
1.
11
15
b1000 7
0;
#801000000
#810000000
1!
1(
0.
01
1;
#820000000
0!
0&
0(
0-
1.
11
05
b111 7
0;
#821000000
#830000000
1!
1(
0.
01
1;
#840000000
0!
1&
0(
1-
1.
11
15
b110 7
0;
#841000000
#850000000
1!
1(
0.
01
1;
#860000000
0!
0&
0(
0-
1.
11
05
b101 7
0;
#861000000
#870000000
1!
1(
0.
01
1;
#880000000
0!
1&
0(
1-
1.
11
15
b100 7
0;
#881000000
#890000000
1!
1(
0.
01
1;
#900000000
0!
0&
0(
0-
1.
11
05
b11 7
0;
#901000000
#910000000
1!
1(
0.
01
1;
#920000000
0!
1&
0(
1-
1.
11
15
b10 7
0;
#921000000
#930000000
1!
1(
0.
01
1;
#940000000
0!
0(
1.
11
b1 7
0;
#941000000
#950000000
1!
1(
0.
01
1;
#960000000
0!
0&
0(
0-
1.
11
05
b0 7
0;
#961000000
#970000000
1!
1(
0.
01
1;
#980000000
0!
1%
1&
0(
1+
1-
1.
10
11
13
15
0;
1>
#981000000
#990000000
1!
1(
0.
01
1;
#1000000000
0!
0(
1.
11
0;
#1001000000
#1010000000
1!
1(
0.
01
1;
#1020000000
0!
0(
1.
11
0;
#1021000000
#1030000000
1!
1(
0.
01
1;
#1040000000
0!
0(
1.
11
0;
#1041000000
#1050000000
1!
1(
0.
01
1;
#1060000000
0!
0(
1.
11
0;
#1061000000
#1070000000
1!
1(
0.
01
1;
#1080000000
0!
0(
1.
11
0;
#1081000000
#1090000000
1!
1(
0.
01
1;
#1100000000
0!
0(
1.
11
0;
#1101000000
#1110000000
1!
1(
0.
01
1;
#1120000000
0!
0(
1.
11
0;
#1121000000
#1130000000
1!
1(
0.
01
1;
#1140000000
0!
0(
1.
11
0;
#1141000000
#1150000000
1!
1(
0.
01
1;
#1160000000
0!
0(
1.
11
0;
#1161000000
#1170000000
1!
1(
0.
01
1;
#1180000000
0!
0(
1.
11
0;
#1181000000
#1190000000
1!
1(
0.
01
1;
#1200000000
0!
0(
1.
11
0;
#1201000000
#1210000000
1!
1(
0.
01
1;
#1220000000
0!
0(
1.
11
0;
#1221000000
0#
0*
0=
#1230000000
1!
1(
0.
01
1;
#1240000000
0!
0(
1.
11
0;
#1241000000
#1250000000
1!
1(
0.
01
1;
#1260000000
0!
0(
1.
11
0;
#1261000000
#1270000000
1!
1(
0.
01
1;
#1280000000
0!
0(
1.
11
0;
#1281000000
#1290000000
1!
1(
0.
01
1;
#1300000000
0!
0(
1.
11
0;
#1301000000
#1310000000
1!
1(
0.
01
1;
#1320000000
0!
0(
1.
11
0;
#1321000000
#1330000000
1!
1(
0.
01
1;
#1340000000
0!
0(
1.
11
0;
#1341000000
#1350000000
1!
1(
0.
01
1;
#1360000000
0!
0(
1.
11
0;
#1361000000
#1370000000
1!
1(
0.
01
1;
#1380000000
0!
0(
1.
11
0;
#1381000000
#1390000000
1!
1(
0.
01
1;
#1400000000
0!
0(
1.
11
0;
#1401000000
#1410000000
1!
1(
0.
01
1;
#1420000000
0!
0(
1.
11
0;
#1421000000
#1430000000
1!
1(
0.
01
1;
#1440000000
0!
0(
1.
11
0;
#1450000000
1!
1(
0.
01
1;
#1460000000
0!
0(
1.
11
0;
#1470000000
1!
1(
0.
01
1;
#1480000000
0!
0(
1.
11
0;
#1490000000
1!
1(
0.
01
1;
#1500000000
0!
0(
1.
11
0;
#1510000000
1!
1(
0.
01
1;
#1520000000
0!
0(
1.
11
0;
#1521000000
1"
b00000000 $
1)
b00000000 ,
b00000000 4
1<
#1530000000
1!
1(
0.
0/
01
02
b11111111111 8
09
1;
0?
#1540000000
0!
0%
0(
0+
1.
00
11
03
b1010 7
0;
0>
#1550000000
1!
1(
0.
01
1;
#1560000000
0!
0(
1.
11
0;
#1561000000
0"
1#
0)
1*
0<
1=
#1570000000
1!
1(
0.
1/
01
12
b00000000011 8
b00000000 :
1;
1?
#1580000000
0!
0&
0(
0-
1.
11
05
b1001 7
0;
#1581000000
#1590000000
1!
1(
0.
01
1;
#1600000000
0!
0(
1.
11
b1000 7
0;
#1601000000
#1610000000
1!
1(
0.
01
1;
#1620000000
0!
0(
1.
11
b111 7
0;
#1621000000
b01111111 $
b01111111 ,
b01111111 4
#1630000000
1!
1(
0.
01
1;
#1640000000
0!
0(
1.
11
b110 7
0;
#1641000000
#1650000000
1!
1(
0.
01
1;
#1660000000
0!
0(
1.
11
b101 7
0;
#1661000000
#1670000000
1!
1(
0.
01
1;
#1680000000
0!
0(
1.
11
b100 7
0;
#1681000000
#1690000000
1!
1(
0.
01
1;
#1700000000
0!
0(
1.
11
b11 7
0;
#1701000000
#1710000000
1!
1(
0.
01
1;
#1720000000
0!
0(
1.
11
b10 7
0;
#1721000000
#1730000000
1!
1(
0.
01
1;
#1740000000
0!
0(
1.
11
b1 7
0;
#1741000000
#1750000000
1!
1(
0.
01
1;
#1760000000
0!
1&
0(
1-
1.
11
15
b0 7
0;
#1761000000
#1770000000
1!
1(
0.
01
1;
#1780000000
0!
1%
0(
1+
1.
10
11
13
0;
1>
#1781000000
1'
