aula_5/serial_out.vhd
-------------------------------------------------------------Unidade de Controle-------------------------------------------------------------
LIBRARY ieee;
USE ieee.numeric_bit.ALL;

ENTITY UC IS
    PORT (
        clock : IN BIT;
        reset, tx_go, tx_done : IN BIT;
        state_bit : OUT BIT
    );

END uc;

ARCHITECTURE behave_uc OF UC IS

    TYPE state IS (Swait, Ssend);
    SIGNAL current_state, next_state : state := Swait;
BEGIN

    PROCESS (clock)
    BEGIN
        IF (clock'event AND clock = '1') THEN
            current_state <= next_state;
        END IF;
    END PROCESS;

    next_state <= Swait WHEN (reset = '1') ELSE
        Ssend WHEN (tx_go = '1') ELSE
        next_state;

    PROCESS (current_state)
    BEGIN
        CASE current_state IS
            WHEN Swait =>
                state_bit <= '0';
            WHEN Ssend =>
                state_bit <= '1';
        END CASE;
    END PROCESS;
END behave_uc;

-------------------------------------------------------------Fluxo de Dados-----------------------------------------------------

LIBRARY ieee;
USE ieee.numeric_bit.ALL;

ENTITY FD IS
    GENERIC (
        POLARITY : BOOLEAN := true;
        width : NATURAL := 7;
        parity : NATURAL := 1;
        stop_bits : NATURAL := 1
    );
    PORT (
        clock : IN BIT;
        state, keep_going : IN BIT;
        tx_done : OUT BIT;
        data : IN bit_vector(width - 1 DOWNTO 0);
        serial_o : OUT BIT
    );
END FD;

ARCHITECTURE behave_fd OF FD IS
    SIGNAL start_bit : BIT;
    SIGNAL counter : INTEGER := 0;
    SIGNAL all_data : bit_vector (width + stop_bits + parity DOWNTO 0); -- with start bit
    SIGNAL parity_bit : BIT := '0';
    SIGNAL backwards_data : bit_vector(width - 1 DOWNTO 0);
BEGIN
    start_bit <= '1' WHEN NOT polarity ELSE
        '0';

    PROCESS (state)
    BEGIN
        IF (state'event) AND (state = '1') THEN
            FOR i IN 0 TO width - 1 LOOP
                backwards_data(i) <= data(width - i - 1);
                parity_bit <= data(i) XOR parity_bit;
            END LOOP;
        ELSIF state = '0' THEN
            parity_bit <= '0';
        END IF;
    END PROCESS;

    all_data (width + parity + stop_bits DOWNTO stop_bits) <= start_bit & backwards_data & NOT parity_bit WHEN state = '1' ELSE
    (OTHERS => '1');

    all_data (stop_bits - 1 DOWNTO 0) <= (OTHERS => '1');

    tx_done <= '1' WHEN counter = 0 ELSE
        '0';

    PROCESS (clock)
    BEGIN
        IF (clock'event AND clock = '1') THEN

            IF state = '1' THEN
                serial_o <= all_data(counter);
            ELSE
                serial_o <= '1';
            END IF;

            IF state = '0' THEN
                counter <= width + stop_bits + parity;
            ELSIF counter > 0 THEN
                counter <= counter - 1;
            ELSIF (counter = 0 AND keep_going = '1') THEN
                counter <= width + stop_bits + parity;
            END IF;

        END IF;
    END PROCESS;
END behave_fd;

-------------------------------------------------------------serial_out-------------------------------------------------------------
LIBRARY ieee;
USE ieee.numeric_bit.ALL;

ENTITY serial_out IS
    GENERIC (
        POLARITY : BOOLEAN := true;
        width : NATURAL := 7;
        parity : NATURAL := 1;
        stop_bits : NATURAL := 1
    );
    PORT (
        clock : IN BIT;
        reset, tx_go : IN BIT;
        tx_done : OUT BIT;
        data : IN bit_vector(width - 1 DOWNTO 0);
        serial_o : OUT BIT
    );
END serial_out;

ARCHITECTURE behave_serial_out OF serial_out IS
    COMPONENT UC IS
        PORT (
            clock : IN BIT;
            reset, tx_go, tx_done : IN BIT;
            state_bit : OUT BIT
        );

    END COMPONENT;
    COMPONENT FD IS
        GENERIC (
            POLARITY : BOOLEAN := true;
            width : NATURAL := 7;
            parity : NATURAL := 1;
            stop_bits : NATURAL := 1
        );
        PORT (
            clock : IN BIT;
            state, keep_going : IN BIT;
            tx_done : OUT BIT;
            data : IN bit_vector(width - 1 DOWNTO 0);
            serial_o : OUT BIT
        );

    END COMPONENT;

    SIGNAL inverted_clock, state, done : BIT := '0';
BEGIN
    inverted_clock <= NOT clock;
    tx_done <= done;
    UC_instance : UC PORT MAP(clock => clock, reset => reset, tx_go => tx_go, tx_done => done, state_bit => state);
    FD_instance : FD GENERIC MAP(polarity, width, parity, stop_bits) PORT MAP(clock => inverted_clock, tx_done => done, state => state, data => data, serial_o => serial_o, keep_going => tx_go);

END behave_serial_out;

aula_5/tx_tb.vhd
LIBRARY ieee;
USE ieee.numeric_bit.ALL;

entity serial_out_tb is
end serial_out_tb;

architecture behavior of serial_out_tb is 
    -- Component Declaration for the Unit Under Test (UUT)
    component serial_out
    generic (
        POLARITY  : boolean := TRUE;
        WIDTH     : natural := 8;
        PARITY    : natural := 1;
        STOP_BITS : natural := 1
    );
    port (
        clock    : in  bit;
        reset    : in  bit;
        tx_go    : in  bit;
        tx_done  : out bit;
        data     : in  bit_vector(WIDTH-1 downto 0);
        serial_o : out bit
    );
    end component;

    component serial_out2
    generic (
        POLARITY  : boolean := TRUE;
        WIDTH     : natural := 8;
        PARITY    : natural := 1;
        STOP_BITS : natural := 1
    );
    port (
        clock    : in  bit;
        reset    : in  bit;
        tx_go    : in  bit;
        tx_done  : out bit;
        data     : in  bit_vector(WIDTH-1 downto 0);
        serial_o : out bit
    );
    end component;

    --Inputs
    signal clock : bit := '0';
    signal reset : bit := '0';
    signal tx_go : bit := '0';
    signal data : bit_vector(7 downto 0);

    --Outputs
    signal tx_done  : bit;
    signal serial_o : bit;
    

    -- Control
    signal finished: bit := '0';
    constant half_period : time := 10 ns;

begin

    dut: serial_out generic map (
            POLARITY  => TRUE,
            WIDTH     => 8,
            PARITY    => 1,
            STOP_BITS => 1
        )
        port map (
            clock    => clock,
            reset    => reset,
            tx_go    => tx_go,
            tx_done  => tx_done,
            data     => data,
            serial_o => serial_o
        );

    clock <= not clock after half_period when finished /= '1' else '0';


    test: process
    begin
        assert false report "Inicio testes";
        
        data  <= "11010101"; --Paridade 0
        reset <= '1';
        wait for 4*half_period;  
        reset <= '0'; 
        tx_go <= '1';
        wait until rising_edge(clock);

        wait until falling_edge(clock); --Amostra no meio do bit
        assert serial_o = '0'
        report "Start Bit falhou";

        tx_go <= '0';

        for i in data'reverse_range loop
            wait until falling_edge(clock);
            assert serial_o = data(i)
            report "serial:" & bit'image(serial_o) & ", esperado:" &bit'image(data(i))&"idx:"&integer'image(i);
        end loop;

        wait until falling_edge(clock);
        assert serial_o = '0'
        report "Teste Paridade Falhou";

        
        wait until falling_edge(clock);
        assert serial_o = '1'
        report "Stop Bit falhou";
        assert tx_done = '1'
        report "Done Falhou";

        report "Fim teste transmissao inicial";

        wait for 10*half_period;

        assert tx_done = '1'
        report "Done Deve se manter ligado";
        

        data  <= "11010101"; --Paridade 0
        reset <= '1';
        wait for 4*half_period;  
        
        reset <= '0'; 
        tx_go <= '1';
        wait until rising_edge(clock);

        wait until falling_edge(clock); --Amostra no meio do bit
        assert serial_o = '0'
        report "Start Bit falhou";

        for i in data'reverse_range loop
            wait until falling_edge(clock);
            assert serial_o = data(i)
            report "serial:" & bit'image(serial_o) & ", esperado:" &bit'image(data(i))&"idx:"&integer'image(i);
        end loop;

        wait until falling_edge(clock);
        assert serial_o = '0'
        report "Teste Paridade Falhou";
        wait until falling_edge(clock);
        assert serial_o = '1'
        report "Stop Bit falhou";

        report "Fim teste reset e transmissao";


        wait for 10*half_period;

        report "Inicio teste metralhadora";

        data  <= "11010101"; --Paridade 0
        reset <= '1';
        wait for 4*half_period;  
        
        reset <= '0'; 
        tx_go <= '1';
        wait until rising_edge(clock);

        for i in 0 to 2 loop
            wait until falling_edge(clock); --Amostra no meio do bit
            assert serial_o = '0'
            report "Start Bit falhou";

            if i = 2 then
                tx_go <= '0';
            end if;

            for i in data'reverse_range loop
                wait until falling_edge(clock);
                assert serial_o = data(i)
                report "serial:" & bit'image(serial_o) & ", esperado:" &bit'image(data(i))&"idx:"&integer'image(i);
            end loop;

            wait until falling_edge(clock);
            assert serial_o = '0'
            report "Teste Paridade Falhou";
            wait until falling_edge(clock);
            assert serial_o = '1'
            report "Stop Bit falhou";
        end loop;


        report "Fim teste metralhadora";


        wait for 10*half_period;

        report "Inicio teste swap data";

        data  <= "00000000"; --Paridade 1
        reset <= '1';
        wait for 4*half_period;  
        
        reset <= '0'; 
        tx_go <= '1';
        wait until rising_edge(clock);
        wait until falling_edge(clock); --Amostra no meio do bit
        assert serial_o = '0'
        report "Start Bit falhou";
        wait until falling_edge(clock); --Amostra no meio do bit
        assert serial_o = '0'
        report "1 Bit falhou";
        wait until falling_edge(clock); --Amostra no meio do bit
        assert serial_o = '0'
        report "2 Bit falhou";

        data <= "01111111"; -- Paridade 0

        wait until falling_edge(clock); --Amostra no meio do bit
        assert serial_o = '0'
        report "3 Bit falhou";
        wait until falling_edge(clock); --Amostra no meio do bit
        assert serial_o = '0'
        report "4 Bit falhou";
        wait until falling_edge(clock); --Amostra no meio do bit
        assert serial_o = '0'
        report "5 Bit falhou";
        wait until falling_edge(clock); --Amostra no meio do bit
        assert serial_o = '0'
        report "6 Bit falhou";
        wait until falling_edge(clock); --Amostra no meio do bit
        assert serial_o = '0'
        report "7 Bit falhou";
        wait until falling_edge(clock); --Amostra no meio do bit
        assert serial_o = '0'
        report "8 Bit falhou";
        wait until falling_edge(clock); --Amostra no meio do bit
        assert serial_o = '1'
        report "Paridade Falhou";
        wait until falling_edge(clock); --Amostra no meio do bit
        assert serial_o = '1'
        report "Stopbit Falhou";


        report "Fim teste swap data";

        finished <= '1';
        wait;
    end process;


end behavior;

aula_5/res.vcd
$date
  Wed Apr 10 10:14:21 2024
$end
$version
  GHDL v0
$end
$timescale
  1 fs
$end
$scope module standard $end
$upscope $end
$scope module numeric_bit $end
$upscope $end
$scope module serial_out_tb $end
$var reg 1 ! clock $end
$var reg 1 " reset $end
$var reg 1 # tx_go $end
$var reg 8 $ data[7:0] $end
$var reg 1 % tx_done $end
$var reg 1 & serial_o $end
$var reg 1 ' finished $end
$scope module dut $end
$var reg 1 ( clock $end
$var reg 1 ) reset $end
$var reg 1 * tx_go $end
$var reg 1 + tx_done $end
$var reg 8 , data[7:0] $end
$var reg 1 - serial_o $end
$var reg 1 . inverted_clock $end
$var reg 1 / state $end
$var reg 1 0 done $end
$scope module uc_instance $end
$var reg 1 1 clock $end
$var reg 1 2 reset $end
$var reg 1 3 tx_go $end
$var reg 1 4 tx_done $end
$var reg 1 5 state_bit $end
$comment current_state is not handled $end
$comment next_state is not handled $end
$upscope $end
$scope module fd_instance $end
$var reg 1 6 clock $end
$var reg 1 7 state $end
$var reg 1 8 keep_going $end
$var reg 1 9 tx_done $end
$var reg 8 : data[7:0] $end
$var reg 1 ; serial_o $end
$var reg 1 < start_bit $end
$var integer 32 = counter $end
$var reg 11 > all_data[10:0] $end
$var reg 1 ? parity_bit $end
$var reg 8 @ backwards_data[7:0] $end
$upscope $end
$upscope $end
$upscope $end
$enddefinitions $end
#0
0!
1"
0#
b11010101 $
0%
1&
0'
0(
1)
0*
0+
b11010101 ,
1-
1.
0/
00
01
12
03
04
05
16
07
08
09
b11010101 :
1;
0<
b1010 =
b11111111111 >
0?
b00000000 @
#10000000
1!
1(
0.
11
06
#20000000
0!
0(
1.
01
16
#30000000
1!
1(
0.
11
06
#40000000
0!
0"
1#
0(
0)
1*
1.
01
02
13
16
18
#50000000
1!
1(
0.
1/
11
15
06
17
b01010101101 >
1?
b10101011 @
#60000000
0!
0&
0(
0-
1.
01
16
0;
b1001 =
#61000000
0#
0*
03
08
#70000000
1!
1(
0.
11
06
#80000000
0!
1&
0(
1-
1.
01
16
1;
b1000 =
#81000000
#90000000
1!
1(
0.
11
06
#100000000
0!
0&
0(
0-
1.
01
16
0;
b111 =
#101000000
#110000000
1!
1(
0.
11
06
#120000000
0!
1&
0(
1-
1.
01
16
1;
b110 =
#121000000
#130000000
1!
1(
0.
11
06
#140000000
0!
0&
0(
0-
1.
01
16
0;
b101 =
#141000000
#150000000
1!
1(
0.
11
06
#160000000
0!
1&
0(
1-
1.
01
16
1;
b100 =
#161000000
#170000000
1!
1(
0.
11
06
#180000000
0!
0&
0(
0-
1.
01
16
0;
b11 =
#181000000
#190000000
1!
1(
0.
11
06
#200000000
0!
1&
0(
1-
1.
01
16
1;
b10 =
#201000000
#210000000
1!
1(
0.
11
06
#220000000
0!
0(
1.
01
16
b1 =
#221000000
#230000000
1!
1(
0.
11
06
#240000000
0!
1%
0&
0(
1+
0-
1.
10
01
14
16
19
0;
b0 =
#241000000
#250000000
1!
1(
0.
11
06
#260000000
0!
1&
0(
1-
1.
01
16
1;
#261000000
#262000000
#270000000
1!
1(
0.
11
06
#280000000
0!
0(
1.
01
16
#290000000
1!
1(
0.
11
06
#300000000
0!
0(
1.
01
16
#310000000
1!
1(
0.
11
06
#320000000
0!
0(
1.
01
16
#330000000
1!
1(
0.
11
06
#340000000
0!
0(
1.
01
16
#350000000
1!
1(
0.
11
06
#360000000
0!
0(
1.
01
16
#362000000
1"
1)
12
#370000000
1!
1(
0.
0/
11
05
06
07
b11111111111 >
0?
#380000000
0!
0%
0(
0+
1.
00
01
04
16
09
b1010 =
#390000000
1!
1(
0.
11
06
#400000000
0!
0(
1.
01
16
#402000000
0"
1#
0)
1*
02
13
18
#410000000
1!
1(
0.
1/
11
15
06
17
b01010101101 >
1?
#420000000
0!
0&
0(
0-
1.
01
16
0;
b1001 =
#421000000
#430000000
1!
1(
0.
11
06
#440000000
0!
1&
0(
1-
1.
01
16
1;
b1000 =
#441000000
#450000000
1!
1(
0.
11
06
#460000000
0!
0&
0(
0-
1.
01
16
0;
b111 =
#461000000
#470000000
1!
1(
0.
11
06
#480000000
0!
1&
0(
1-
1.
01
16
1;
b110 =
#481000000
#490000000
1!
1(
0.
11
06
#500000000
0!
0&
0(
0-
1.
01
16
0;
b101 =
#501000000
#510000000
1!
1(
0.
11
06
#520000000
0!
1&
0(
1-
1.
01
16
1;
b100 =
#521000000
#530000000
1!
1(
0.
11
06
#540000000
0!
0&
0(
0-
1.
01
16
0;
b11 =
#541000000
#550000000
1!
1(
0.
11
06
#560000000
0!
1&
0(
1-
1.
01
16
1;
b10 =
#561000000
#570000000
1!
1(
0.
11
06
#580000000
0!
0(
1.
01
16
b1 =
#581000000
#590000000
1!
1(
0.
11
06
#600000000
0!
1%
0&
0(
1+
0-
1.
10
01
14
16
19
0;
b0 =
#601000000
#610000000
1!
1(
0.
11
06
#620000000
0!
0%
1&
0(
0+
1-
1.
00
01
04
16
09
1;
b1010 =
#621000000
#630000000
1!
1(
0.
11
06
#640000000
0!
0&
0(
0-
1.
01
16
0;
b1001 =
#650000000
1!
1(
0.
11
06
#660000000
0!
1&
0(
1-
1.
01
16
1;
b1000 =
#670000000
1!
1(
0.
11
06
#680000000
0!
0&
0(
0-
1.
01
16
0;
b111 =
#690000000
1!
1(
0.
11
06
#700000000
0!
1&
0(
1-
1.
01
16
1;
b110 =
#710000000
1!
1(
0.
11
06
#720000000
0!
0&
0(
0-
1.
01
16
0;
b101 =
#721000000
1"
1)
12
#730000000
1!
1(
0.
0/
11
05
06
07
b11111111111 >
0?
#740000000
0!
1&
0(
1-
1.
01
16
1;
b1010 =
#750000000
1!
1(
0.
11
06
#760000000
0!
0(
1.
01
16
#761000000
0"
0)
02
#770000000
1!
1(
0.
1/
11
15
06
17
b01010101101 >
1?
#780000000
0!
0&
0(
0-
1.
01
16
0;
b1001 =
#781000000
#790000000
1!
1(
0.
11
06
#800000000
0!
1&
0(
1-
1.
01
16
1;
b1000 =
#801000000
#810000000
1!
1(
0.
11
06
#820000000
0!
0&
0(
0-
1.
01
16
0;
b111 =
#821000000
#830000000
1!
1(
0.
11
06
#840000000
0!
1&
0(
1-
1.
01
16
1;
b110 =
#841000000
#850000000
1!
1(
0.
11
06
#860000000
0!
0&
0(
0-
1.
01
16
0;
b101 =
#861000000
#870000000
1!
1(
0.
11
06
#880000000
0!
1&
0(
1-
1.
01
16
1;
b100 =
#881000000
#890000000
1!
1(
0.
11
06
#900000000
0!
0&
0(
0-
1.
01
16
0;
b11 =
#901000000
#910000000
1!
1(
0.
11
06
#920000000
0!
1&
0(
1-
1.
01
16
1;
b10 =
#921000000
#930000000
1!
1(
0.
11
06
#940000000
0!
0(
1.
01
16
b1 =
#941000000
#950000000
1!
1(
0.
11
06
#960000000
0!
1%
0&
0(
1+
0-
1.
10
01
14
16
19
0;
b0 =
#961000000
#970000000
1!
1(
0.
11
06
#980000000
0!
0%
1&
0(
0+
1-
1.
00
01
04
16
09
1;
b1010 =
#981000000
#990000000
1!
1(
0.
11
06
#1000000000
0!
0&
0(
0-
1.
01
16
0;
b1001 =
#1001000000
#1010000000
1!
1(
0.
11
06
#1020000000
0!
1&
0(
1-
1.
01
16
1;
b1000 =
#1021000000
#1030000000
1!
1(
0.
11
06
#1040000000
0!
0&
0(
0-
1.
01
16
0;
b111 =
#1041000000
#1050000000
1!
1(
0.
11
06
#1060000000
0!
1&
0(
1-
1.
01
16
1;
b110 =
#1061000000
#1070000000
1!
1(
0.
11
06
#1080000000
0!
0&
0(
0-
1.
01
16
0;
b101 =
#1081000000
#1090000000
1!
1(
0.
11
06
#1100000000
0!
1&
0(
1-
1.
01
16
1;
b100 =
#1101000000
#1110000000
1!
1(
0.
11
06
#1120000000
0!
0&
0(
0-
1.
01
16
0;
b11 =
#1121000000
#1130000000
1!
1(
0.
11
06
#1140000000
0!
1&
0(
1-
1.
01
16
1;
b10 =
#1141000000
#1150000000
1!
1(
0.
11
06
#1160000000
0!
0(
1.
01
16
b1 =
#1161000000
#1170000000
1!
1(
0.
11
06
#1180000000
0!
1%
0&
0(
1+
0-
1.
10
01
14
16
19
0;
b0 =
#1181000000
#1190000000
1!
1(
0.
11
06
#1200000000
0!
0%
1&
0(
0+
1-
1.
00
01
04
16
09
1;
b1010 =
#1201000000
#1210000000
1!
1(
0.
11
06
#1220000000
0!
0&
0(
0-
1.
01
16
0;
b1001 =
#1221000000
0#
0*
03
08
#1230000000
1!
1(
0.
11
06
#1240000000
0!
1&
0(
1-
1.
01
16
1;
b1000 =
#1241000000
#1250000000
1!
1(
0.
11
06
#1260000000
0!
0&
0(
0-
1.
01
16
0;
b111 =
#1261000000
#1270000000
1!
1(
0.
11
06
#1280000000
0!
1&
0(
1-
1.
01
16
1;
b110 =
#1281000000
#1290000000
1!
1(
0.
11
06
#1300000000
0!
0&
0(
0-
1.
01
16
0;
b101 =
#1301000000
#1310000000
1!
1(
0.
11
06
#1320000000
0!
1&
0(
1-
1.
01
16
1;
b100 =
#1321000000
#1330000000
1!
1(
0.
11
06
#1340000000
0!
0&
0(
0-
1.
01
16
0;
b11 =
#1341000000
#1350000000
1!
1(
0.
11
06
#1360000000
0!
1&
0(
1-
1.
01
16
1;
b10 =
#1361000000
#1370000000
1!
1(
0.
11
06
#1380000000
0!
0(
1.
01
16
b1 =
#1381000000
#1390000000
1!
1(
0.
11
06
#1400000000
0!
1%
0&
0(
1+
0-
1.
10
01
14
16
19
0;
b0 =
#1401000000
#1410000000
1!
1(
0.
11
06
#1420000000
0!
1&
0(
1-
1.
01
16
1;
#1421000000
#1430000000
1!
1(
0.
11
06
#1440000000
0!
0(
1.
01
16
#1450000000
1!
1(
0.
11
06
#1460000000
0!
0(
1.
01
16
#1470000000
1!
1(
0.
11
06
#1480000000
0!
0(
1.
01
16
#1490000000
1!
1(
0.
11
06
#1500000000
0!
0(
1.
01
16
#1510000000
1!
1(
0.
11
06
#1520000000
0!
0(
1.
01
16
#1521000000
1"
b00000000 $
1)
b00000000 ,
12
b00000000 :
#1530000000
1!
1(
0.
0/
11
05
06
07
b11111111111 >
0?
#1540000000
0!
0%
0(
0+
1.
00
01
04
16
09
b1010 =
#1550000000
1!
1(
0.
11
06
#1560000000
0!
0(
1.
01
16
#1561000000
0"
1#
0)
1*
02
13
18
#1570000000
1!
1(
0.
1/
11
15
06
17
b00000000011 >
b00000000 @
#1580000000
0!
0&
0(
0-
1.
01
16
0;
b1001 =
#1581000000
#1590000000
1!
1(
0.
11
06
#1600000000
0!
0(
1.
01
16
b1000 =
#1601000000
#1610000000
1!
1(
0.
11
06
#1620000000
0!
0(
1.
01
16
b111 =
#1621000000
b01111111 $
b01111111 ,
b01111111 :
#1630000000
1!
1(
0.
11
06
#1640000000
0!
0(
1.
01
16
b110 =
#1641000000
#1650000000
1!
1(
0.
11
06
#1660000000
0!
0(
1.
01
16
b101 =
#1661000000
#1670000000
1!
1(
0.
11
06
#1680000000
0!
0(
1.
01
16
b100 =
#1681000000
#1690000000
1!
1(
0.
11
06
#1700000000
0!
0(
1.
01
16
b11 =
#1701000000
#1710000000
1!
1(
0.
11
06
#1720000000
0!
0(
1.
01
16
b10 =
#1721000000
#1730000000
1!
1(
0.
11
06
#1740000000
0!
0(
1.
01
16
b1 =
#1741000000
#1750000000
1!
1(
0.
11
06
#1760000000
0!
1%
1&
0(
1+
1-
1.
10
01
14
16
19
1;
b0 =
#1761000000
#1770000000
1!
1(
0.
11
06
#1780000000
0!
0%
0(
0+
1.
00
01
04
16
09
b1010 =
#1781000000
1'
